{
    "0": "get_dressed", 
    "1": "prepare_brunch", 
    "2": "answering_phone", 
    "3": "go_to_bed", 
    "4": "get_drink", 
    "5": "search_keys", 
    "6": "eat_brunch", 
    "7": "prepare_for_leaving", 
    "8": "setting_up_sensors", 
    "9": "on_phone", 
    "10": "shaving", 
    "11": "leave_house", 
    "12": "wash_dishes", 
    "13": "prepare_dinner", 
    "14": "install_sensor", 
    "15": "use_toilet", 
    "16": "eat_dinner", 
    "17": "take_shower", 
    "18": "faster_kitchen_camera", 
    "19": "play_piano", 
    "20": "brush_teeth", 
    "21": "drop_dish", 
    "22": "unpacking", 
    "23": "shave", 
    "24": "put_clothes_in_washing_machine", 
    "25": "relax", 
    "26": "get_snack", 
    "27": "eating", 
    "28": "take_medication", 
    "29": "prepare_lunch", 
    "30": "prepare_breakfast"
}